substitutionciphers/__init__.py
substitutionciphers/griffinere.py
substitutionciphers-2.0.0.dist-info/METADATA
substitutionciphers-2.0.0.dist-info/WHEEL
substitutionciphers-2.0.0.dist-info/RECORD
