Metadata-Version: 2.4
Name: substitutionciphers
Version: 2.0.0
Summary: The Griffinere cipher is a custom encryption algorithm in C# designed for reversible, base64-normalized encryption using a repeating key. Inspired by the Vigenère cipher, it adds configurable alphabet support, input validation, and padding-based encryption length enforcement.
Project-URL: Homepage, https://github.com/RileyG00/Ciphers
Project-URL: Source, https://github.com/RileyG00/Ciphers/tree/add-python
Author-email: Riley Griffin <riley.griffin00@outlook.com>
License: MIT
Classifier: License :: OSI Approved :: MIT License
Classifier: Programming Language :: Python :: 3
Classifier: Topic :: Security :: Cryptography
Requires-Python: >=3.9
